{"page":481,"line":{"1":[{"id":40339,"position":1,"audio_url":"wbw\/041_039_001.mp3","char_type_name":"word","code_v1":"\ufb51","page_number":481,"line_number":1,"text":"\ufb51","translation":{"text":"dan dari","language_name":"indonesian"},"transliteration":{"text":"wamin","language_name":"english"},"verse":"39","chapter":"41"},{"id":40340,"position":2,"audio_url":"wbw\/041_039_002.mp3","char_type_name":"word","code_v1":"\ufb52","page_number":481,"line_number":1,"text":"\ufb52","translation":{"text":"tanda-tanda-Nya","language_name":"indonesian"},"transliteration":{"text":"\u0101y\u0101tihi","language_name":"english"},"verse":"39","chapter":"41"},{"id":40341,"position":3,"audio_url":"wbw\/041_039_003.mp3","char_type_name":"word","code_v1":"\ufb53","page_number":481,"line_number":1,"text":"\ufb53","translation":{"text":"bahwasanya kamu","language_name":"indonesian"},"transliteration":{"text":"annaka","language_name":"english"},"verse":"39","chapter":"41"},{"id":40342,"position":4,"audio_url":"wbw\/041_039_004.mp3","char_type_name":"word","code_v1":"\ufb54","page_number":481,"line_number":1,"text":"\ufb54","translation":{"text":"melihat","language_name":"indonesian"},"transliteration":{"text":"tar\u0101","language_name":"english"},"verse":"39","chapter":"41"},{"id":40343,"position":5,"audio_url":"wbw\/041_039_005.mp3","char_type_name":"word","code_v1":"\ufb55","page_number":481,"line_number":1,"text":"\ufb55","translation":{"text":"bumi","language_name":"indonesian"},"transliteration":{"text":"l-ar\u1e0da","language_name":"english"},"verse":"39","chapter":"41"},{"id":40344,"position":6,"audio_url":"wbw\/041_039_006.mp3","char_type_name":"word","code_v1":"\ufb56","page_number":481,"line_number":1,"text":"\ufb56","translation":{"text":"tandus","language_name":"indonesian"},"transliteration":{"text":"kh\u0101shi\u02bfatan","language_name":"english"},"verse":"39","chapter":"41"},{"id":40345,"position":7,"audio_url":"wbw\/041_039_007.mp3","char_type_name":"word","code_v1":"\ufb57","page_number":481,"line_number":1,"text":"\ufb57","translation":{"text":"maka apabila","language_name":"indonesian"},"transliteration":{"text":"fa-idh\u0101","language_name":"english"},"verse":"39","chapter":"41"},{"id":40346,"position":8,"audio_url":"wbw\/041_039_008.mp3","char_type_name":"word","code_v1":"\ufb58","page_number":481,"line_number":1,"text":"\ufb58","translation":{"text":"Kami turunkan","language_name":"indonesian"},"transliteration":{"text":"anzaln\u0101","language_name":"english"},"verse":"39","chapter":"41"},{"id":40347,"position":9,"audio_url":"wbw\/041_039_009.mp3","char_type_name":"word","code_v1":"\ufb59","page_number":481,"line_number":1,"text":"\ufb59","translation":{"text":"atasnya","language_name":"indonesian"},"transliteration":{"text":"\u02bfalayh\u0101","language_name":"english"},"verse":"39","chapter":"41"},{"id":40348,"position":10,"audio_url":"wbw\/041_039_010.mp3","char_type_name":"word","code_v1":"\ufb5a","page_number":481,"line_number":1,"text":"\ufb5a","translation":{"text":"air","language_name":"indonesian"},"transliteration":{"text":"l-m\u0101a","language_name":"english"},"verse":"39","chapter":"41"}],"2":[{"id":40349,"position":11,"audio_url":"wbw\/041_039_011.mp3","char_type_name":"word","code_v1":"\ufb5b","page_number":481,"line_number":2,"text":"\ufb5b","translation":{"text":"ia bergerak","language_name":"indonesian"},"transliteration":{"text":"ih'tazzat","language_name":"english"},"verse":"39","chapter":"41"},{"id":40350,"position":12,"audio_url":"wbw\/041_039_012.mp3","char_type_name":"word","code_v1":"\ufb5c\ufb5d","page_number":481,"line_number":2,"text":"\ufb5c\ufb5d","translation":{"text":"dan berkembang","language_name":"indonesian"},"transliteration":{"text":"warabat","language_name":"english"},"verse":"39","chapter":"41"},{"id":40352,"position":13,"audio_url":"wbw\/041_039_014.mp3","char_type_name":"word","code_v1":"\ufb5e","page_number":481,"line_number":2,"text":"\ufb5e","translation":{"text":"sesungguhnya","language_name":"indonesian"},"transliteration":{"text":"inna","language_name":"english"},"verse":"39","chapter":"41"},{"id":40353,"position":14,"audio_url":"wbw\/041_039_015.mp3","char_type_name":"word","code_v1":"\ufb5f","page_number":481,"line_number":2,"text":"\ufb5f","translation":{"text":"yang","language_name":"indonesian"},"transliteration":{"text":"alladh\u012b","language_name":"english"},"verse":"39","chapter":"41"},{"id":40354,"position":15,"audio_url":"wbw\/041_039_016.mp3","char_type_name":"word","code_v1":"\ufb60","page_number":481,"line_number":2,"text":"\ufb60","translation":{"text":"menghidupkannya","language_name":"indonesian"},"transliteration":{"text":"a\u1e25y\u0101h\u0101","language_name":"english"},"verse":"39","chapter":"41"},{"id":40355,"position":16,"audio_url":"wbw\/041_039_017.mp3","char_type_name":"word","code_v1":"\ufb61","page_number":481,"line_number":2,"text":"\ufb61","translation":{"text":"tentu dapat menghidupkan","language_name":"indonesian"},"transliteration":{"text":"lamu\u1e25'y\u012b","language_name":"english"},"verse":"39","chapter":"41"},{"id":40356,"position":17,"audio_url":"wbw\/041_039_018.mp3","char_type_name":"word","code_v1":"\ufb62\ufb63","page_number":481,"line_number":2,"text":"\ufb62\ufb63","translation":{"text":"yang mati","language_name":"indonesian"},"transliteration":{"text":"l-mawt\u0101","language_name":"english"},"verse":"39","chapter":"41"},{"id":40358,"position":18,"audio_url":"wbw\/041_039_020.mp3","char_type_name":"word","code_v1":"\ufb64","page_number":481,"line_number":2,"text":"\ufb64","translation":{"text":"sesungguhnya Dia","language_name":"indonesian"},"transliteration":{"text":"innahu","language_name":"english"},"verse":"39","chapter":"41"},{"id":40359,"position":19,"audio_url":"wbw\/041_039_021.mp3","char_type_name":"word","code_v1":"\ufb65","page_number":481,"line_number":2,"text":"\ufb65","translation":{"text":"atas","language_name":"indonesian"},"transliteration":{"text":"\u02bfal\u0101","language_name":"english"},"verse":"39","chapter":"41"},{"id":40360,"position":20,"audio_url":"wbw\/041_039_022.mp3","char_type_name":"word","code_v1":"\ufb66","page_number":481,"line_number":2,"text":"\ufb66","translation":{"text":"segala","language_name":"indonesian"},"transliteration":{"text":"kulli","language_name":"english"},"verse":"39","chapter":"41"},{"id":40361,"position":21,"audio_url":"wbw\/041_039_023.mp3","char_type_name":"word","code_v1":"\ufb67","page_number":481,"line_number":2,"text":"\ufb67","translation":{"text":"sesuatu","language_name":"indonesian"},"transliteration":{"text":"shayin","language_name":"english"},"verse":"39","chapter":"41"}],"3":[{"id":40362,"position":22,"audio_url":"wbw\/041_039_024.mp3","char_type_name":"word","code_v1":"\ufb68","page_number":481,"line_number":3,"text":"\ufb68","translation":{"text":"Maha Kuasa","language_name":"indonesian"},"transliteration":{"text":"qad\u012brun","language_name":"english"},"verse":"39","chapter":"41"},{"id":40363,"position":23,"audio_url":null,"char_type_name":"end","code_v1":"\ufb69","page_number":481,"line_number":3,"text":"\ufb69","translation":{"text":"(39)","language_name":"indonesian"},"transliteration":{"text":null,"language_name":"english"},"verse":"39","chapter":"41"},{"id":41073,"position":1,"audio_url":"wbw\/041_040_001.mp3","char_type_name":"word","code_v1":"\ufb6a","page_number":481,"line_number":3,"text":"\ufb6a","translation":{"text":"sesungguhnya","language_name":"indonesian"},"transliteration":{"text":"inna","language_name":"english"},"verse":"40","chapter":"41"},{"id":41074,"position":2,"audio_url":"wbw\/041_040_002.mp3","char_type_name":"word","code_v1":"\ufb6b","page_number":481,"line_number":3,"text":"\ufb6b","translation":{"text":"orang-orang yang","language_name":"indonesian"},"transliteration":{"text":"alladh\u012bna","language_name":"english"},"verse":"40","chapter":"41"},{"id":41075,"position":3,"audio_url":"wbw\/041_040_003.mp3","char_type_name":"word","code_v1":"\ufb6c","page_number":481,"line_number":3,"text":"\ufb6c","translation":{"text":"mereka ingkar","language_name":"indonesian"},"transliteration":{"text":"yul'\u1e25id\u016bna","language_name":"english"},"verse":"40","chapter":"41"},{"id":41076,"position":4,"audio_url":"wbw\/041_040_004.mp3","char_type_name":"word","code_v1":"\ufb6d","page_number":481,"line_number":3,"text":"\ufb6d","translation":{"text":"pada","language_name":"indonesian"},"transliteration":{"text":"f\u012b","language_name":"english"},"verse":"40","chapter":"41"},{"id":41077,"position":5,"audio_url":"wbw\/041_040_005.mp3","char_type_name":"word","code_v1":"\ufb6e","page_number":481,"line_number":3,"text":"\ufb6e","translation":{"text":"ayat-ayat Kami","language_name":"indonesian"},"transliteration":{"text":"\u0101y\u0101tin\u0101","language_name":"english"},"verse":"40","chapter":"41"},{"id":41078,"position":6,"audio_url":"wbw\/041_040_006.mp3","char_type_name":"word","code_v1":"\ufb6f","page_number":481,"line_number":3,"text":"\ufb6f","translation":{"text":"tidak","language_name":"indonesian"},"transliteration":{"text":"l\u0101","language_name":"english"},"verse":"40","chapter":"41"},{"id":41079,"position":7,"audio_url":"wbw\/041_040_007.mp3","char_type_name":"word","code_v1":"\ufb70","page_number":481,"line_number":3,"text":"\ufb70","translation":{"text":"mereka tersembunyi","language_name":"indonesian"},"transliteration":{"text":"yakhfawna","language_name":"english"},"verse":"40","chapter":"41"},{"id":41080,"position":8,"audio_url":"wbw\/041_040_008.mp3","char_type_name":"word","code_v1":"\ufb71\ufb72","page_number":481,"line_number":3,"text":"\ufb71\ufb72","translation":{"text":"dari\/atas Kami","language_name":"indonesian"},"transliteration":{"text":"\u02bfalayn\u0101","language_name":"english"},"verse":"40","chapter":"41"},{"id":41082,"position":9,"audio_url":"wbw\/041_040_010.mp3","char_type_name":"word","code_v1":"\ufb73","page_number":481,"line_number":3,"text":"\ufb73","translation":{"text":"apakah maka orang","language_name":"indonesian"},"transliteration":{"text":"afaman","language_name":"english"},"verse":"40","chapter":"41"}],"4":[{"id":41083,"position":10,"audio_url":"wbw\/041_040_011.mp3","char_type_name":"word","code_v1":"\ufb74","page_number":481,"line_number":4,"text":"\ufb74","translation":{"text":"ia dilemparkan","language_name":"indonesian"},"transliteration":{"text":"yul'q\u0101","language_name":"english"},"verse":"40","chapter":"41"},{"id":41084,"position":11,"audio_url":"wbw\/041_040_012.mp3","char_type_name":"word","code_v1":"\ufb75","page_number":481,"line_number":4,"text":"\ufb75","translation":{"text":"dalam","language_name":"indonesian"},"transliteration":{"text":"f\u012b","language_name":"english"},"verse":"40","chapter":"41"},{"id":41085,"position":12,"audio_url":"wbw\/041_040_013.mp3","char_type_name":"word","code_v1":"\ufb76","page_number":481,"line_number":4,"text":"\ufb76","translation":{"text":"neraka","language_name":"indonesian"},"transliteration":{"text":"l-n\u0101ri","language_name":"english"},"verse":"40","chapter":"41"},{"id":41086,"position":13,"audio_url":"wbw\/041_040_014.mp3","char_type_name":"word","code_v1":"\ufb77","page_number":481,"line_number":4,"text":"\ufb77","translation":{"text":"lebih baik","language_name":"indonesian"},"transliteration":{"text":"khayrun","language_name":"english"},"verse":"40","chapter":"41"},{"id":41087,"position":14,"audio_url":"wbw\/041_040_015.mp3","char_type_name":"word","code_v1":"\ufb78","page_number":481,"line_number":4,"text":"\ufb78","translation":{"text":"ataukah\/apakah","language_name":"indonesian"},"transliteration":{"text":"am","language_name":"english"},"verse":"40","chapter":"41"},{"id":41088,"position":15,"audio_url":"wbw\/041_040_016.mp3","char_type_name":"word","code_v1":"\ufb79","page_number":481,"line_number":4,"text":"\ufb79","translation":{"text":"orang","language_name":"indonesian"},"transliteration":{"text":"man","language_name":"english"},"verse":"40","chapter":"41"},{"id":41089,"position":16,"audio_url":"wbw\/041_040_017.mp3","char_type_name":"word","code_v1":"\ufb7a","page_number":481,"line_number":4,"text":"\ufb7a","translation":{"text":"ia datang","language_name":"indonesian"},"transliteration":{"text":"yat\u012b","language_name":"english"},"verse":"40","chapter":"41"},{"id":41090,"position":17,"audio_url":"wbw\/041_040_018.mp3","char_type_name":"word","code_v1":"\ufb7b","page_number":481,"line_number":4,"text":"\ufb7b","translation":{"text":"aman","language_name":"indonesian"},"transliteration":{"text":"\u0101minan","language_name":"english"},"verse":"40","chapter":"41"},{"id":41091,"position":18,"audio_url":"wbw\/041_040_019.mp3","char_type_name":"word","code_v1":"\ufb7c","page_number":481,"line_number":4,"text":"\ufb7c","translation":{"text":"pada hari","language_name":"indonesian"},"transliteration":{"text":"yawma","language_name":"english"},"verse":"40","chapter":"41"},{"id":41092,"position":19,"audio_url":"wbw\/041_040_020.mp3","char_type_name":"word","code_v1":"\ufb7d\ufb7e","page_number":481,"line_number":4,"text":"\ufb7d\ufb7e","translation":{"text":"kiamat","language_name":"indonesian"},"transliteration":{"text":"l-qiy\u0101mati","language_name":"english"},"verse":"40","chapter":"41"},{"id":41094,"position":20,"audio_url":"wbw\/041_040_022.mp3","char_type_name":"word","code_v1":"\ufb7f","page_number":481,"line_number":4,"text":"\ufb7f","translation":{"text":"berbuatlah","language_name":"indonesian"},"transliteration":{"text":"i\u02bf'mal\u016b","language_name":"english"},"verse":"40","chapter":"41"},{"id":41095,"position":21,"audio_url":"wbw\/041_040_023.mp3","char_type_name":"word","code_v1":"\ufb80","page_number":481,"line_number":4,"text":"\ufb80","translation":{"text":"apa yang","language_name":"indonesian"},"transliteration":{"text":"m\u0101","language_name":"english"},"verse":"40","chapter":"41"},{"id":41096,"position":22,"audio_url":"wbw\/041_040_024.mp3","char_type_name":"word","code_v1":"\ufb81\ufb82","page_number":481,"line_number":4,"text":"\ufb81\ufb82","translation":{"text":"kalian kehendaki","language_name":"indonesian"},"transliteration":{"text":"shi'tum","language_name":"english"},"verse":"40","chapter":"41"}],"5":[{"id":41098,"position":23,"audio_url":"wbw\/041_040_026.mp3","char_type_name":"word","code_v1":"\ufb83","page_number":481,"line_number":5,"text":"\ufb83","translation":{"text":"sesungguhnya Dia","language_name":"indonesian"},"transliteration":{"text":"innahu","language_name":"english"},"verse":"40","chapter":"41"},{"id":41099,"position":24,"audio_url":"wbw\/041_040_027.mp3","char_type_name":"word","code_v1":"\ufb84","page_number":481,"line_number":5,"text":"\ufb84","translation":{"text":"terhadap apa","language_name":"indonesian"},"transliteration":{"text":"bim\u0101","language_name":"english"},"verse":"40","chapter":"41"},{"id":41100,"position":25,"audio_url":"wbw\/041_040_028.mp3","char_type_name":"word","code_v1":"\ufb85","page_number":481,"line_number":5,"text":"\ufb85","translation":{"text":"kamu kerjakan","language_name":"indonesian"},"transliteration":{"text":"ta\u02bfmal\u016bna","language_name":"english"},"verse":"40","chapter":"41"},{"id":41101,"position":26,"audio_url":"wbw\/041_040_029.mp3","char_type_name":"word","code_v1":"\ufb86","page_number":481,"line_number":5,"text":"\ufb86","translation":{"text":"Maha Melihat","language_name":"indonesian"},"transliteration":{"text":"ba\u1e63\u012brun","language_name":"english"},"verse":"40","chapter":"41"},{"id":41102,"position":27,"audio_url":null,"char_type_name":"end","code_v1":"\ufb87","page_number":481,"line_number":5,"text":"\ufb87","translation":{"text":"(40)","language_name":"indonesian"},"transliteration":{"text":null,"language_name":"english"},"verse":"40","chapter":"41"},{"id":41967,"position":1,"audio_url":"wbw\/041_041_001.mp3","char_type_name":"word","code_v1":"\ufb88","page_number":481,"line_number":5,"text":"\ufb88","translation":{"text":"sesungguhnya","language_name":"indonesian"},"transliteration":{"text":"inna","language_name":"english"},"verse":"41","chapter":"41"},{"id":41968,"position":2,"audio_url":"wbw\/041_041_002.mp3","char_type_name":"word","code_v1":"\ufb89","page_number":481,"line_number":5,"text":"\ufb89","translation":{"text":"orang-orang yang","language_name":"indonesian"},"transliteration":{"text":"alladh\u012bna","language_name":"english"},"verse":"41","chapter":"41"},{"id":41969,"position":3,"audio_url":"wbw\/041_041_003.mp3","char_type_name":"word","code_v1":"\ufb8a","page_number":481,"line_number":5,"text":"\ufb8a","translation":{"text":"kafir\/ingkar","language_name":"indonesian"},"transliteration":{"text":"kafar\u016b","language_name":"english"},"verse":"41","chapter":"41"},{"id":41970,"position":4,"audio_url":"wbw\/041_041_004.mp3","char_type_name":"word","code_v1":"\ufb8b","page_number":481,"line_number":5,"text":"\ufb8b","translation":{"text":"dengan peringatan\/Al Qur'an","language_name":"indonesian"},"transliteration":{"text":"bil-dhik'ri","language_name":"english"},"verse":"41","chapter":"41"},{"id":41971,"position":5,"audio_url":"wbw\/041_041_005.mp3","char_type_name":"word","code_v1":"\ufb8c","page_number":481,"line_number":5,"text":"\ufb8c","translation":{"text":"ketika","language_name":"indonesian"},"transliteration":{"text":"lamm\u0101","language_name":"english"},"verse":"41","chapter":"41"},{"id":41972,"position":6,"audio_url":"wbw\/041_041_006.mp3","char_type_name":"word","code_v1":"\ufb8d\ufb8e","page_number":481,"line_number":5,"text":"\ufb8d\ufb8e","translation":{"text":"ia datang kepada mereka","language_name":"indonesian"},"transliteration":{"text":"j\u0101ahum","language_name":"english"},"verse":"41","chapter":"41"}],"6":[{"id":41974,"position":7,"audio_url":"wbw\/041_041_008.mp3","char_type_name":"word","code_v1":"\ufb8f","page_number":481,"line_number":6,"text":"\ufb8f","translation":{"text":"dan sesungguhnya ia (Al Qur'an)","language_name":"indonesian"},"transliteration":{"text":"wa-innahu","language_name":"english"},"verse":"41","chapter":"41"},{"id":41975,"position":8,"audio_url":"wbw\/041_041_009.mp3","char_type_name":"word","code_v1":"\ufb90","page_number":481,"line_number":6,"text":"\ufb90","translation":{"text":"sungguh kitab","language_name":"indonesian"},"transliteration":{"text":"lakit\u0101bun","language_name":"english"},"verse":"41","chapter":"41"},{"id":41976,"position":9,"audio_url":"wbw\/041_041_010.mp3","char_type_name":"word","code_v1":"\ufb91","page_number":481,"line_number":6,"text":"\ufb91","translation":{"text":"mulia","language_name":"indonesian"},"transliteration":{"text":"\u02bfaz\u012bzun","language_name":"english"},"verse":"41","chapter":"41"},{"id":41977,"position":10,"audio_url":null,"char_type_name":"end","code_v1":"\ufb92","page_number":481,"line_number":6,"text":"\ufb92","translation":{"text":"(41)","language_name":"indonesian"},"transliteration":{"text":null,"language_name":"english"},"verse":"41","chapter":"41"},{"id":42699,"position":1,"audio_url":"wbw\/041_042_001.mp3","char_type_name":"word","code_v1":"\ufb93","page_number":481,"line_number":6,"text":"\ufb93","translation":{"text":"tidak","language_name":"indonesian"},"transliteration":{"text":"l\u0101","language_name":"english"},"verse":"42","chapter":"41"},{"id":42700,"position":2,"audio_url":"wbw\/041_042_002.mp3","char_type_name":"word","code_v1":"\ufb94","page_number":481,"line_number":6,"text":"\ufb94","translation":{"text":"datang kepadanya","language_name":"indonesian"},"transliteration":{"text":"yat\u012bhi","language_name":"english"},"verse":"42","chapter":"41"},{"id":42701,"position":3,"audio_url":"wbw\/041_042_003.mp3","char_type_name":"word","code_v1":"\ufb95","page_number":481,"line_number":6,"text":"\ufb95","translation":{"text":"kebathilan","language_name":"indonesian"},"transliteration":{"text":"l-b\u0101\u1e6dilu","language_name":"english"},"verse":"42","chapter":"41"},{"id":42702,"position":4,"audio_url":"wbw\/041_042_004.mp3","char_type_name":"word","code_v1":"\ufb96","page_number":481,"line_number":6,"text":"\ufb96","translation":{"text":"dari","language_name":"indonesian"},"transliteration":{"text":"min","language_name":"english"},"verse":"42","chapter":"41"},{"id":42703,"position":5,"audio_url":"wbw\/041_042_005.mp3","char_type_name":"word","code_v1":"\ufb97","page_number":481,"line_number":6,"text":"\ufb97","translation":{"text":"antara","language_name":"indonesian"},"transliteration":{"text":"bayni","language_name":"english"},"verse":"42","chapter":"41"},{"id":42704,"position":6,"audio_url":"wbw\/041_042_006.mp3","char_type_name":"word","code_v1":"\ufb98","page_number":481,"line_number":6,"text":"\ufb98","translation":{"text":"depannya","language_name":"indonesian"},"transliteration":{"text":"yadayhi","language_name":"english"},"verse":"42","chapter":"41"},{"id":42705,"position":7,"audio_url":"wbw\/041_042_007.mp3","char_type_name":"word","code_v1":"\ufb99","page_number":481,"line_number":6,"text":"\ufb99","translation":{"text":"dan tidak","language_name":"indonesian"},"transliteration":{"text":"wal\u0101","language_name":"english"},"verse":"42","chapter":"41"},{"id":42706,"position":8,"audio_url":"wbw\/041_042_008.mp3","char_type_name":"word","code_v1":"\ufb9a","page_number":481,"line_number":6,"text":"\ufb9a","translation":{"text":"dari","language_name":"indonesian"},"transliteration":{"text":"min","language_name":"english"},"verse":"42","chapter":"41"}],"7":[{"id":42707,"position":9,"audio_url":"wbw\/041_042_009.mp3","char_type_name":"word","code_v1":"\ufb9b\ufb9c","page_number":481,"line_number":7,"text":"\ufb9b\ufb9c","translation":{"text":"belakangnya","language_name":"indonesian"},"transliteration":{"text":"khalfihi","language_name":"english"},"verse":"42","chapter":"41"},{"id":42709,"position":10,"audio_url":"wbw\/041_042_011.mp3","char_type_name":"word","code_v1":"\ufb9d","page_number":481,"line_number":7,"text":"\ufb9d","translation":{"text":"diturunkan","language_name":"indonesian"},"transliteration":{"text":"tanz\u012blun","language_name":"english"},"verse":"42","chapter":"41"},{"id":42710,"position":11,"audio_url":"wbw\/041_042_012.mp3","char_type_name":"word","code_v1":"\ufb9e","page_number":481,"line_number":7,"text":"\ufb9e","translation":{"text":"dari","language_name":"indonesian"},"transliteration":{"text":"min","language_name":"english"},"verse":"42","chapter":"41"},{"id":42711,"position":12,"audio_url":"wbw\/041_042_013.mp3","char_type_name":"word","code_v1":"\ufb9f","page_number":481,"line_number":7,"text":"\ufb9f","translation":{"text":"Yang Maha Bijaksana","language_name":"indonesian"},"transliteration":{"text":"\u1e25ak\u012bmin","language_name":"english"},"verse":"42","chapter":"41"},{"id":42712,"position":13,"audio_url":"wbw\/041_042_014.mp3","char_type_name":"word","code_v1":"\ufba0","page_number":481,"line_number":7,"text":"\ufba0","translation":{"text":"Maha Terpuji","language_name":"indonesian"},"transliteration":{"text":"\u1e25am\u012bdin","language_name":"english"},"verse":"42","chapter":"41"},{"id":42713,"position":14,"audio_url":null,"char_type_name":"end","code_v1":"\ufba1","page_number":481,"line_number":7,"text":"\ufba1","translation":{"text":"(42)","language_name":"indonesian"},"transliteration":{"text":null,"language_name":"english"},"verse":"42","chapter":"41"},{"id":44006,"position":1,"audio_url":"wbw\/041_043_001.mp3","char_type_name":"word","code_v1":"\ufba2","page_number":481,"line_number":7,"text":"\ufba2","translation":{"text":"tidak","language_name":"indonesian"},"transliteration":{"text":"m\u0101","language_name":"english"},"verse":"43","chapter":"41"},{"id":44007,"position":2,"audio_url":"wbw\/041_043_002.mp3","char_type_name":"word","code_v1":"\ufba3","page_number":481,"line_number":7,"text":"\ufba3","translation":{"text":"dikatakan","language_name":"indonesian"},"transliteration":{"text":"yuq\u0101lu","language_name":"english"},"verse":"43","chapter":"41"},{"id":44008,"position":3,"audio_url":"wbw\/041_043_003.mp3","char_type_name":"word","code_v1":"\ufba4","page_number":481,"line_number":7,"text":"\ufba4","translation":{"text":"kepadamu","language_name":"indonesian"},"transliteration":{"text":"laka","language_name":"english"},"verse":"43","chapter":"41"},{"id":44009,"position":4,"audio_url":"wbw\/041_043_004.mp3","char_type_name":"word","code_v1":"\ufba5","page_number":481,"line_number":7,"text":"\ufba5","translation":{"text":"kecuali","language_name":"indonesian"},"transliteration":{"text":"ill\u0101","language_name":"english"},"verse":"43","chapter":"41"},{"id":44010,"position":5,"audio_url":"wbw\/041_043_005.mp3","char_type_name":"word","code_v1":"\ufba6","page_number":481,"line_number":7,"text":"\ufba6","translation":{"text":"apa","language_name":"indonesian"},"transliteration":{"text":"m\u0101","language_name":"english"},"verse":"43","chapter":"41"},{"id":44011,"position":6,"audio_url":"wbw\/041_043_006.mp3","char_type_name":"word","code_v1":"\ufba7","page_number":481,"line_number":7,"text":"\ufba7","translation":{"text":"sesungguhnya","language_name":"indonesian"},"transliteration":{"text":"qad","language_name":"english"},"verse":"43","chapter":"41"},{"id":44012,"position":7,"audio_url":"wbw\/041_043_007.mp3","char_type_name":"word","code_v1":"\ufba8","page_number":481,"line_number":7,"text":"\ufba8","translation":{"text":"dikatakan","language_name":"indonesian"},"transliteration":{"text":"q\u012bla","language_name":"english"},"verse":"43","chapter":"41"}],"8":[{"id":44013,"position":8,"audio_url":"wbw\/041_043_008.mp3","char_type_name":"word","code_v1":"\ufba9","page_number":481,"line_number":8,"text":"\ufba9","translation":{"text":"kepada rasul-rasul","language_name":"indonesian"},"transliteration":{"text":"lilrrusuli","language_name":"english"},"verse":"43","chapter":"41"},{"id":44014,"position":9,"audio_url":"wbw\/041_043_009.mp3","char_type_name":"word","code_v1":"\ufbaa","page_number":481,"line_number":8,"text":"\ufbaa","translation":{"text":"dari","language_name":"indonesian"},"transliteration":{"text":"min","language_name":"english"},"verse":"43","chapter":"41"},{"id":44015,"position":10,"audio_url":"wbw\/041_043_010.mp3","char_type_name":"word","code_v1":"\ufbab\ufbac","page_number":481,"line_number":8,"text":"\ufbab\ufbac","translation":{"text":"sebelum kamu","language_name":"indonesian"},"transliteration":{"text":"qablika","language_name":"english"},"verse":"43","chapter":"41"},{"id":44017,"position":11,"audio_url":"wbw\/041_043_012.mp3","char_type_name":"word","code_v1":"\ufbad","page_number":481,"line_number":8,"text":"\ufbad","translation":{"text":"sesungguhnya","language_name":"indonesian"},"transliteration":{"text":"inna","language_name":"english"},"verse":"43","chapter":"41"},{"id":44018,"position":12,"audio_url":"wbw\/041_043_013.mp3","char_type_name":"word","code_v1":"\ufbae","page_number":481,"line_number":8,"text":"\ufbae","translation":{"text":"Tuhanmu","language_name":"indonesian"},"transliteration":{"text":"rabbaka","language_name":"english"},"verse":"43","chapter":"41"},{"id":44019,"position":13,"audio_url":"wbw\/041_043_014.mp3","char_type_name":"word","code_v1":"\ufbaf","page_number":481,"line_number":8,"text":"\ufbaf","translation":{"text":"benar-benar mempunyai","language_name":"indonesian"},"transliteration":{"text":"ladh\u016b","language_name":"english"},"verse":"43","chapter":"41"},{"id":44020,"position":14,"audio_url":"wbw\/041_043_015.mp3","char_type_name":"word","code_v1":"\ufbb0","page_number":481,"line_number":8,"text":"\ufbb0","translation":{"text":"ampunan","language_name":"indonesian"},"transliteration":{"text":"maghfiratin","language_name":"english"},"verse":"43","chapter":"41"},{"id":44021,"position":15,"audio_url":"wbw\/041_043_016.mp3","char_type_name":"word","code_v1":"\ufbb1","page_number":481,"line_number":8,"text":"\ufbb1","translation":{"text":"dan mempunyai","language_name":"indonesian"},"transliteration":{"text":"wadh\u016b","language_name":"english"},"verse":"43","chapter":"41"},{"id":44022,"position":16,"audio_url":"wbw\/041_043_017.mp3","char_type_name":"word","code_v1":"\ufbd3","page_number":481,"line_number":8,"text":"\ufbd3","translation":{"text":"siksaan\/hukuman","language_name":"indonesian"},"transliteration":{"text":"\u02bfiq\u0101bin","language_name":"english"},"verse":"43","chapter":"41"},{"id":44023,"position":17,"audio_url":"wbw\/041_043_018.mp3","char_type_name":"word","code_v1":"\ufbd4","page_number":481,"line_number":8,"text":"\ufbd4","translation":{"text":"pedih","language_name":"indonesian"},"transliteration":{"text":"al\u012bmin","language_name":"english"},"verse":"43","chapter":"41"},{"id":44024,"position":18,"audio_url":null,"char_type_name":"end","code_v1":"\ufbd5","page_number":481,"line_number":8,"text":"\ufbd5","translation":{"text":"(43)","language_name":"indonesian"},"transliteration":{"text":null,"language_name":"english"},"verse":"43","chapter":"41"}],"9":[{"id":44233,"position":1,"audio_url":"wbw\/041_044_001.mp3","char_type_name":"word","code_v1":"\ufbd6","page_number":481,"line_number":9,"text":"\ufbd6","translation":{"text":"dan jika","language_name":"indonesian"},"transliteration":{"text":"walaw","language_name":"english"},"verse":"44","chapter":"41"},{"id":44234,"position":2,"audio_url":"wbw\/041_044_002.mp3","char_type_name":"word","code_v1":"\ufbd7","page_number":481,"line_number":9,"text":"\ufbd7","translation":{"text":"Kami jadikannya","language_name":"indonesian"},"transliteration":{"text":"ja\u02bfaln\u0101hu","language_name":"english"},"verse":"44","chapter":"41"},{"id":44235,"position":3,"audio_url":"wbw\/041_044_003.mp3","char_type_name":"word","code_v1":"\ufbd8","page_number":481,"line_number":9,"text":"\ufbd8","translation":{"text":"bacaan","language_name":"indonesian"},"transliteration":{"text":"qur'\u0101nan","language_name":"english"},"verse":"44","chapter":"41"},{"id":44236,"position":4,"audio_url":"wbw\/041_044_004.mp3","char_type_name":"word","code_v1":"\ufbd9","page_number":481,"line_number":9,"text":"\ufbd9","translation":{"text":"bahasa asing\/selain bahasa Arab","language_name":"indonesian"},"transliteration":{"text":"a\u02bfjamiyyan","language_name":"english"},"verse":"44","chapter":"41"},{"id":44237,"position":5,"audio_url":"wbw\/041_044_005.mp3","char_type_name":"word","code_v1":"\ufbda","page_number":481,"line_number":9,"text":"\ufbda","translation":{"text":"tentu mereka mengatakan","language_name":"indonesian"},"transliteration":{"text":"laq\u0101l\u016b","language_name":"english"},"verse":"44","chapter":"41"},{"id":44238,"position":6,"audio_url":"wbw\/041_044_006.mp3","char_type_name":"word","code_v1":"\ufbdb","page_number":481,"line_number":9,"text":"\ufbdb","translation":{"text":"mengapa tidak","language_name":"indonesian"},"transliteration":{"text":"lawl\u0101","language_name":"english"},"verse":"44","chapter":"41"},{"id":44239,"position":7,"audio_url":"wbw\/041_044_007.mp3","char_type_name":"word","code_v1":"\ufbdc","page_number":481,"line_number":9,"text":"\ufbdc","translation":{"text":"dijelaskan","language_name":"indonesian"},"transliteration":{"text":"fu\u1e63\u1e63ilat","language_name":"english"},"verse":"44","chapter":"41"},{"id":44240,"position":8,"audio_url":"wbw\/041_044_008.mp3","char_type_name":"word","code_v1":"\ufbdd\ufbde","page_number":481,"line_number":9,"text":"\ufbdd\ufbde","translation":{"text":"ayat-ayatnya","language_name":"indonesian"},"transliteration":{"text":"\u0101y\u0101tuhu","language_name":"english"},"verse":"44","chapter":"41"},{"id":44242,"position":9,"audio_url":"wbw\/041_044_010.mp3","char_type_name":"word","code_v1":"\ufbdf","page_number":481,"line_number":9,"text":"\ufbdf","translation":{"text":"apakah bahasa asing\/selain bahasa Arab","language_name":"indonesian"},"transliteration":{"text":"\u0101\u02bf'jamiyyun","language_name":"english"},"verse":"44","chapter":"41"}],"10":[{"id":44243,"position":10,"audio_url":"wbw\/041_044_011.mp3","char_type_name":"word","code_v1":"\ufbe0\ufbe1","page_number":481,"line_number":10,"text":"\ufbe0\ufbe1","translation":{"text":"dan orang Arab\/bahasa Arab","language_name":"indonesian"},"transliteration":{"text":"wa\u02bfarabiyyun","language_name":"english"},"verse":"44","chapter":"41"},{"id":44245,"position":11,"audio_url":"wbw\/041_044_013.mp3","char_type_name":"word","code_v1":"\ufbe2","page_number":481,"line_number":10,"text":"\ufbe2","translation":{"text":"katakanlah","language_name":"indonesian"},"transliteration":{"text":"qul","language_name":"english"},"verse":"44","chapter":"41"},{"id":44246,"position":12,"audio_url":"wbw\/041_044_014.mp3","char_type_name":"word","code_v1":"\ufbe3","page_number":481,"line_number":10,"text":"\ufbe3","translation":{"text":"ia\/Al Qur'an","language_name":"indonesian"},"transliteration":{"text":"huwa","language_name":"english"},"verse":"44","chapter":"41"},{"id":44247,"position":13,"audio_url":"wbw\/041_044_015.mp3","char_type_name":"word","code_v1":"\ufbe4","page_number":481,"line_number":10,"text":"\ufbe4","translation":{"text":"bagi orang-orang yang","language_name":"indonesian"},"transliteration":{"text":"lilladh\u012bna","language_name":"english"},"verse":"44","chapter":"41"},{"id":44248,"position":14,"audio_url":"wbw\/041_044_016.mp3","char_type_name":"word","code_v1":"\ufbe5","page_number":481,"line_number":10,"text":"\ufbe5","translation":{"text":"beriman","language_name":"indonesian"},"transliteration":{"text":"\u0101man\u016b","language_name":"english"},"verse":"44","chapter":"41"},{"id":44249,"position":15,"audio_url":"wbw\/041_044_017.mp3","char_type_name":"word","code_v1":"\ufbe6","page_number":481,"line_number":10,"text":"\ufbe6","translation":{"text":"petunjuk","language_name":"indonesian"},"transliteration":{"text":"hudan","language_name":"english"},"verse":"44","chapter":"41"},{"id":44250,"position":16,"audio_url":"wbw\/041_044_018.mp3","char_type_name":"word","code_v1":"\ufbe7\ufbe8","page_number":481,"line_number":10,"text":"\ufbe7\ufbe8","translation":{"text":"dan penawar\/obat","language_name":"indonesian"},"transliteration":{"text":"washif\u0101on","language_name":"english"},"verse":"44","chapter":"41"},{"id":44252,"position":17,"audio_url":"wbw\/041_044_020.mp3","char_type_name":"word","code_v1":"\ufbe9","page_number":481,"line_number":10,"text":"\ufbe9","translation":{"text":"dan orang-orang yang","language_name":"indonesian"},"transliteration":{"text":"wa-alladh\u012bna","language_name":"english"},"verse":"44","chapter":"41"}],"11":[{"id":44253,"position":18,"audio_url":"wbw\/041_044_021.mp3","char_type_name":"word","code_v1":"\ufbea","page_number":481,"line_number":11,"text":"\ufbea","translation":{"text":"tidak","language_name":"indonesian"},"transliteration":{"text":"l\u0101","language_name":"english"},"verse":"44","chapter":"41"},{"id":44254,"position":19,"audio_url":"wbw\/041_044_022.mp3","char_type_name":"word","code_v1":"\ufbeb","page_number":481,"line_number":11,"text":"\ufbeb","translation":{"text":"mereka beriman","language_name":"indonesian"},"transliteration":{"text":"yu'min\u016bna","language_name":"english"},"verse":"44","chapter":"41"},{"id":44255,"position":20,"audio_url":"wbw\/041_044_023.mp3","char_type_name":"word","code_v1":"\ufbec","page_number":481,"line_number":11,"text":"\ufbec","translation":{"text":"pada","language_name":"indonesian"},"transliteration":{"text":"f\u012b","language_name":"english"},"verse":"44","chapter":"41"},{"id":44256,"position":21,"audio_url":"wbw\/041_044_024.mp3","char_type_name":"word","code_v1":"\ufbed","page_number":481,"line_number":11,"text":"\ufbed","translation":{"text":"telinga mereka","language_name":"indonesian"},"transliteration":{"text":"\u0101dh\u0101nihim","language_name":"english"},"verse":"44","chapter":"41"},{"id":44257,"position":22,"audio_url":"wbw\/041_044_025.mp3","char_type_name":"word","code_v1":"\ufbee","page_number":481,"line_number":11,"text":"\ufbee","translation":{"text":"sumbat","language_name":"indonesian"},"transliteration":{"text":"waqrun","language_name":"english"},"verse":"44","chapter":"41"},{"id":44258,"position":23,"audio_url":"wbw\/041_044_026.mp3","char_type_name":"word","code_v1":"\ufbef","page_number":481,"line_number":11,"text":"\ufbef","translation":{"text":"dan ia\/Al Qur'an","language_name":"indonesian"},"transliteration":{"text":"wahuwa","language_name":"english"},"verse":"44","chapter":"41"},{"id":44259,"position":24,"audio_url":"wbw\/041_044_027.mp3","char_type_name":"word","code_v1":"\ufbf0","page_number":481,"line_number":11,"text":"\ufbf0","translation":{"text":"atas mereka","language_name":"indonesian"},"transliteration":{"text":"\u02bfalayhim","language_name":"english"},"verse":"44","chapter":"41"},{"id":44260,"position":25,"audio_url":"wbw\/041_044_028.mp3","char_type_name":"word","code_v1":"\ufbf1\ufbf2","page_number":481,"line_number":11,"text":"\ufbf1\ufbf2","translation":{"text":"buta\/kegelapan","language_name":"indonesian"},"transliteration":{"text":"\u02bfaman","language_name":"english"},"verse":"44","chapter":"41"},{"id":44262,"position":26,"audio_url":"wbw\/041_044_030.mp3","char_type_name":"word","code_v1":"\ufbf3","page_number":481,"line_number":11,"text":"\ufbf3","translation":{"text":"mereka itu","language_name":"indonesian"},"transliteration":{"text":"ul\u0101ika","language_name":"english"},"verse":"44","chapter":"41"}],"12":[{"id":44263,"position":27,"audio_url":"wbw\/041_044_031.mp3","char_type_name":"word","code_v1":"\ufbf4","page_number":481,"line_number":12,"text":"\ufbf4","translation":{"text":"mereka dipanggil","language_name":"indonesian"},"transliteration":{"text":"yun\u0101dawna","language_name":"english"},"verse":"44","chapter":"41"},{"id":44264,"position":28,"audio_url":"wbw\/041_044_032.mp3","char_type_name":"word","code_v1":"\ufbf5","page_number":481,"line_number":12,"text":"\ufbf5","translation":{"text":"dari","language_name":"indonesian"},"transliteration":{"text":"min","language_name":"english"},"verse":"44","chapter":"41"},{"id":44265,"position":29,"audio_url":"wbw\/041_044_033.mp3","char_type_name":"word","code_v1":"\ufbf6","page_number":481,"line_number":12,"text":"\ufbf6","translation":{"text":"tempat","language_name":"indonesian"},"transliteration":{"text":"mak\u0101nin","language_name":"english"},"verse":"44","chapter":"41"},{"id":44266,"position":30,"audio_url":"wbw\/041_044_034.mp3","char_type_name":"word","code_v1":"\ufbf7","page_number":481,"line_number":12,"text":"\ufbf7","translation":{"text":"yang jauh","language_name":"indonesian"},"transliteration":{"text":"ba\u02bf\u012bdin","language_name":"english"},"verse":"44","chapter":"41"},{"id":44267,"position":31,"audio_url":null,"char_type_name":"end","code_v1":"\ufbf8","page_number":481,"line_number":12,"text":"\ufbf8","translation":{"text":"(44)","language_name":"indonesian"},"transliteration":{"text":null,"language_name":"english"},"verse":"44","chapter":"41"},{"id":44955,"position":1,"audio_url":"wbw\/041_045_001.mp3","char_type_name":"word","code_v1":"\ufbf9","page_number":481,"line_number":12,"text":"\ufbf9","translation":{"text":"dan sesungguhnya","language_name":"indonesian"},"transliteration":{"text":"walaqad","language_name":"english"},"verse":"45","chapter":"41"},{"id":44956,"position":2,"audio_url":"wbw\/041_045_002.mp3","char_type_name":"word","code_v1":"\ufbfa","page_number":481,"line_number":12,"text":"\ufbfa","translation":{"text":"telah Kami berikan","language_name":"indonesian"},"transliteration":{"text":"\u0101tayn\u0101","language_name":"english"},"verse":"45","chapter":"41"},{"id":44957,"position":3,"audio_url":"wbw\/041_045_003.mp3","char_type_name":"word","code_v1":"\ufbfb","page_number":481,"line_number":12,"text":"\ufbfb","translation":{"text":"Musa","language_name":"indonesian"},"transliteration":{"text":"m\u016bs\u0101","language_name":"english"},"verse":"45","chapter":"41"},{"id":44958,"position":4,"audio_url":"wbw\/041_045_004.mp3","char_type_name":"word","code_v1":"\ufbfc","page_number":481,"line_number":12,"text":"\ufbfc","translation":{"text":"kitab","language_name":"indonesian"},"transliteration":{"text":"l-kit\u0101ba","language_name":"english"},"verse":"45","chapter":"41"}],"13":[{"id":44959,"position":5,"audio_url":"wbw\/041_045_005.mp3","char_type_name":"word","code_v1":"\ufbfd","page_number":481,"line_number":13,"text":"\ufbfd","translation":{"text":"maka ia diperselisihkan","language_name":"indonesian"},"transliteration":{"text":"fa-ukh'tulifa","language_name":"english"},"verse":"45","chapter":"41"},{"id":44960,"position":6,"audio_url":"wbw\/041_045_006.mp3","char_type_name":"word","code_v1":"\ufbfe\ufbff","page_number":481,"line_number":13,"text":"\ufbfe\ufbff","translation":{"text":"didalamnya","language_name":"indonesian"},"transliteration":{"text":"f\u012bhi","language_name":"english"},"verse":"45","chapter":"41"},{"id":44962,"position":7,"audio_url":"wbw\/041_045_008.mp3","char_type_name":"word","code_v1":"\ufc00","page_number":481,"line_number":13,"text":"\ufc00","translation":{"text":"dan jika tidak","language_name":"indonesian"},"transliteration":{"text":"walawl\u0101","language_name":"english"},"verse":"45","chapter":"41"},{"id":44963,"position":8,"audio_url":"wbw\/041_045_009.mp3","char_type_name":"word","code_v1":"\ufc01","page_number":481,"line_number":13,"text":"\ufc01","translation":{"text":"kalimat\/ketetapan","language_name":"indonesian"},"transliteration":{"text":"kalimatun","language_name":"english"},"verse":"45","chapter":"41"},{"id":44964,"position":9,"audio_url":"wbw\/041_045_010.mp3","char_type_name":"word","code_v1":"\ufc02","page_number":481,"line_number":13,"text":"\ufc02","translation":{"text":"telah lewat\/terdahulu","language_name":"indonesian"},"transliteration":{"text":"sabaqat","language_name":"english"},"verse":"45","chapter":"41"},{"id":44965,"position":10,"audio_url":"wbw\/041_045_011.mp3","char_type_name":"word","code_v1":"\ufc03","page_number":481,"line_number":13,"text":"\ufc03","translation":{"text":"dari","language_name":"indonesian"},"transliteration":{"text":"min","language_name":"english"},"verse":"45","chapter":"41"},{"id":44966,"position":11,"audio_url":"wbw\/041_045_012.mp3","char_type_name":"word","code_v1":"\ufc04","page_number":481,"line_number":13,"text":"\ufc04","translation":{"text":"Tuhanmu","language_name":"indonesian"},"transliteration":{"text":"rabbika","language_name":"english"},"verse":"45","chapter":"41"},{"id":44967,"position":12,"audio_url":"wbw\/041_045_013.mp3","char_type_name":"word","code_v1":"\ufc05","page_number":481,"line_number":13,"text":"\ufc05","translation":{"text":"tentu diputuskan","language_name":"indonesian"},"transliteration":{"text":"laqu\u1e0diya","language_name":"english"},"verse":"45","chapter":"41"}],"14":[{"id":44968,"position":13,"audio_url":"wbw\/041_045_014.mp3","char_type_name":"word","code_v1":"\ufc06\ufc07","page_number":481,"line_number":14,"text":"\ufc06\ufc07","translation":{"text":"diantara mereka","language_name":"indonesian"},"transliteration":{"text":"baynahum","language_name":"english"},"verse":"45","chapter":"41"},{"id":44970,"position":14,"audio_url":"wbw\/041_045_016.mp3","char_type_name":"word","code_v1":"\ufc08","page_number":481,"line_number":14,"text":"\ufc08","translation":{"text":"dan sesungguhnya mereka","language_name":"indonesian"},"transliteration":{"text":"wa-innahum","language_name":"english"},"verse":"45","chapter":"41"},{"id":44971,"position":15,"audio_url":"wbw\/041_045_017.mp3","char_type_name":"word","code_v1":"\ufc09","page_number":481,"line_number":14,"text":"\ufc09","translation":{"text":"benar-benar dalam","language_name":"indonesian"},"transliteration":{"text":"laf\u012b","language_name":"english"},"verse":"45","chapter":"41"},{"id":44972,"position":16,"audio_url":"wbw\/041_045_018.mp3","char_type_name":"word","code_v1":"\ufc0a","page_number":481,"line_number":14,"text":"\ufc0a","translation":{"text":"keraguan","language_name":"indonesian"},"transliteration":{"text":"shakkin","language_name":"english"},"verse":"45","chapter":"41"},{"id":44973,"position":17,"audio_url":"wbw\/041_045_019.mp3","char_type_name":"word","code_v1":"\ufc0b","page_number":481,"line_number":14,"text":"\ufc0b","translation":{"text":"dari padanya","language_name":"indonesian"},"transliteration":{"text":"min'hu","language_name":"english"},"verse":"45","chapter":"41"},{"id":44974,"position":18,"audio_url":"wbw\/041_045_020.mp3","char_type_name":"word","code_v1":"\ufc0c","page_number":481,"line_number":14,"text":"\ufc0c","translation":{"text":"kebingungan","language_name":"indonesian"},"transliteration":{"text":"mur\u012bbin","language_name":"english"},"verse":"45","chapter":"41"},{"id":44975,"position":19,"audio_url":null,"char_type_name":"end","code_v1":"\ufc0d","page_number":481,"line_number":14,"text":"\ufc0d","translation":{"text":"(45)","language_name":"indonesian"},"transliteration":{"text":null,"language_name":"english"},"verse":"45","chapter":"41"},{"id":45716,"position":1,"audio_url":"wbw\/041_046_001.mp3","char_type_name":"word","code_v1":"\ufc0e","page_number":481,"line_number":14,"text":"\ufc0e","translation":{"text":"barang siapa","language_name":"indonesian"},"transliteration":{"text":"man","language_name":"english"},"verse":"46","chapter":"41"},{"id":45717,"position":2,"audio_url":"wbw\/041_046_002.mp3","char_type_name":"word","code_v1":"\ufc0f","page_number":481,"line_number":14,"text":"\ufc0f","translation":{"text":"berbuat","language_name":"indonesian"},"transliteration":{"text":"\u02bfamila","language_name":"english"},"verse":"46","chapter":"41"},{"id":45718,"position":3,"audio_url":"wbw\/041_046_003.mp3","char_type_name":"word","code_v1":"\ufc10","page_number":481,"line_number":14,"text":"\ufc10","translation":{"text":"kebaikan","language_name":"indonesian"},"transliteration":{"text":"\u1e63\u0101li\u1e25an","language_name":"english"},"verse":"46","chapter":"41"}],"15":[{"id":45719,"position":4,"audio_url":"wbw\/041_046_004.mp3","char_type_name":"word","code_v1":"\ufc11\ufc12","page_number":481,"line_number":15,"text":"\ufc11\ufc12","translation":{"text":"maka untuk dirinya sendiri","language_name":"indonesian"},"transliteration":{"text":"falinafsihi","language_name":"english"},"verse":"46","chapter":"41"},{"id":45721,"position":5,"audio_url":"wbw\/041_046_006.mp3","char_type_name":"word","code_v1":"\ufc13","page_number":481,"line_number":15,"text":"\ufc13","translation":{"text":"dan barang siapa","language_name":"indonesian"},"transliteration":{"text":"waman","language_name":"english"},"verse":"46","chapter":"41"},{"id":45722,"position":6,"audio_url":"wbw\/041_046_007.mp3","char_type_name":"word","code_v1":"\ufc14","page_number":481,"line_number":15,"text":"\ufc14","translation":{"text":"berbuat jahat","language_name":"indonesian"},"transliteration":{"text":"as\u0101a","language_name":"english"},"verse":"46","chapter":"41"},{"id":45723,"position":7,"audio_url":"wbw\/041_046_008.mp3","char_type_name":"word","code_v1":"\ufc15\ufc16","page_number":481,"line_number":15,"text":"\ufc15\ufc16","translation":{"text":"maka atasnya","language_name":"indonesian"},"transliteration":{"text":"fa\u02bfalayh\u0101","language_name":"english"},"verse":"46","chapter":"41"},{"id":45725,"position":8,"audio_url":"wbw\/041_046_010.mp3","char_type_name":"word","code_v1":"\ufc17","page_number":481,"line_number":15,"text":"\ufc17","translation":{"text":"dan tidaklah","language_name":"indonesian"},"transliteration":{"text":"wam\u0101","language_name":"english"},"verse":"46","chapter":"41"},{"id":45726,"position":9,"audio_url":"wbw\/041_046_011.mp3","char_type_name":"word","code_v1":"\ufc18","page_number":481,"line_number":15,"text":"\ufc18","translation":{"text":"Tuhanmu","language_name":"indonesian"},"transliteration":{"text":"rabbuka","language_name":"english"},"verse":"46","chapter":"41"},{"id":45727,"position":10,"audio_url":"wbw\/041_046_012.mp3","char_type_name":"word","code_v1":"\ufc19","page_number":481,"line_number":15,"text":"\ufc19","translation":{"text":"berbuat aniaya","language_name":"indonesian"},"transliteration":{"text":"bi\u1e93all\u0101min","language_name":"english"},"verse":"46","chapter":"41"},{"id":45728,"position":11,"audio_url":"wbw\/041_046_013.mp3","char_type_name":"word","code_v1":"\ufc1a","page_number":481,"line_number":15,"text":"\ufc1a","translation":{"text":"terhadap hamba-hambanya","language_name":"indonesian"},"transliteration":{"text":"lil'\u02bfab\u012bdi","language_name":"english"},"verse":"46","chapter":"41"},{"id":45729,"position":12,"audio_url":null,"char_type_name":"end","code_v1":"\ufc1b","page_number":481,"line_number":15,"text":"\ufc1b","translation":{"text":"(46)","language_name":"indonesian"},"transliteration":{"text":null,"language_name":"english"},"verse":"46","chapter":"41"}]},"word":[{"line":1,"word":0},{"line":1,"word":1},{"line":1,"word":2},{"line":1,"word":3},{"line":1,"word":4},{"line":1,"word":5},{"line":1,"word":6},{"line":1,"word":7},{"line":1,"word":8},{"line":1,"word":9},{"line":2,"word":0},{"line":2,"word":1},{"line":2,"word":2},{"line":2,"word":3},{"line":2,"word":4},{"line":2,"word":5},{"line":2,"word":6},{"line":2,"word":7},{"line":2,"word":8},{"line":2,"word":9},{"line":2,"word":10},{"line":3,"word":0},{"line":3,"word":2},{"line":3,"word":3},{"line":3,"word":4},{"line":3,"word":5},{"line":3,"word":6},{"line":3,"word":7},{"line":3,"word":8},{"line":3,"word":9},{"line":3,"word":10},{"line":4,"word":0},{"line":4,"word":1},{"line":4,"word":2},{"line":4,"word":3},{"line":4,"word":4},{"line":4,"word":5},{"line":4,"word":6},{"line":4,"word":7},{"line":4,"word":8},{"line":4,"word":9},{"line":4,"word":10},{"line":4,"word":11},{"line":4,"word":12},{"line":5,"word":0},{"line":5,"word":1},{"line":5,"word":2},{"line":5,"word":3},{"line":5,"word":5},{"line":5,"word":6},{"line":5,"word":7},{"line":5,"word":8},{"line":5,"word":9},{"line":5,"word":10},{"line":6,"word":0},{"line":6,"word":1},{"line":6,"word":2},{"line":6,"word":4},{"line":6,"word":5},{"line":6,"word":6},{"line":6,"word":7},{"line":6,"word":8},{"line":6,"word":9},{"line":6,"word":10},{"line":6,"word":11},{"line":7,"word":0},{"line":7,"word":1},{"line":7,"word":2},{"line":7,"word":3},{"line":7,"word":4},{"line":7,"word":6},{"line":7,"word":7},{"line":7,"word":8},{"line":7,"word":9},{"line":7,"word":10},{"line":7,"word":11},{"line":7,"word":12},{"line":8,"word":0},{"line":8,"word":1},{"line":8,"word":2},{"line":8,"word":3},{"line":8,"word":4},{"line":8,"word":5},{"line":8,"word":6},{"line":8,"word":7},{"line":8,"word":8},{"line":8,"word":9},{"line":9,"word":0},{"line":9,"word":1},{"line":9,"word":2},{"line":9,"word":3},{"line":9,"word":4},{"line":9,"word":5},{"line":9,"word":6},{"line":9,"word":7},{"line":9,"word":8},{"line":10,"word":0},{"line":10,"word":1},{"line":10,"word":2},{"line":10,"word":3},{"line":10,"word":4},{"line":10,"word":5},{"line":10,"word":6},{"line":10,"word":7},{"line":11,"word":0},{"line":11,"word":1},{"line":11,"word":2},{"line":11,"word":3},{"line":11,"word":4},{"line":11,"word":5},{"line":11,"word":6},{"line":11,"word":7},{"line":11,"word":8},{"line":12,"word":0},{"line":12,"word":1},{"line":12,"word":2},{"line":12,"word":3},{"line":12,"word":5},{"line":12,"word":6},{"line":12,"word":7},{"line":12,"word":8},{"line":13,"word":0},{"line":13,"word":1},{"line":13,"word":2},{"line":13,"word":3},{"line":13,"word":4},{"line":13,"word":5},{"line":13,"word":6},{"line":13,"word":7},{"line":14,"word":0},{"line":14,"word":1},{"line":14,"word":2},{"line":14,"word":3},{"line":14,"word":4},{"line":14,"word":5},{"line":14,"word":7},{"line":14,"word":8},{"line":14,"word":9},{"line":15,"word":0},{"line":15,"word":1},{"line":15,"word":2},{"line":15,"word":3},{"line":15,"word":4},{"line":15,"word":5},{"line":15,"word":6},{"line":15,"word":7}]}